boy/__init__.py
boy/call_me.py
ymj_test1-0.2.dist-info/METADATA
ymj_test1-0.2.dist-info/WHEEL
ymj_test1-0.2.dist-info/top_level.txt
ymj_test1-0.2.dist-info/RECORD
