Metadata-Version: 2.1
Name: ymj-test1
Version: 0.2
Summary: 颜满俊，李立
Author: ymj
License: UNKNOWN
Platform: UNKNOWN
